.scrutinizer.yml
.travis.yml
CONTRIBUTING.rst
HISTORY.rst
LICENSE
MANIFEST.in
README.rst
dev-requirements.txt
setup.cfg
setup.py
tox.ini
docs/design.rst
docs/releasing.rst
libmt94x/__init__.py
libmt94x/convenience.py
libmt94x/currency_codes.py
libmt94x/document.py
libmt94x/fields.py
libmt94x/info_acct_owner_subfields.py
libmt94x/remittance_info.py
libmt94x/serializer.py
libmt94x/statement_line_subfields.py
libmt94x/textutil.py
libmt94x/transaction_codes.py
libmt94x/transfer_failed_codes.py
libmt94x/writer.py
python_libmt94x.egg-info/PKG-INFO
python_libmt94x.egg-info/SOURCES.txt
python_libmt94x.egg-info/dependency_links.txt
python_libmt94x.egg-info/not-zip-safe
python_libmt94x.egg-info/requires.txt
python_libmt94x.egg-info/top_level.txt