Metadata-Version: 1.1
Name: python-libmt94x
Version: 0.3.4
Summary: This library generates bank statements in MT940/MT942 format
Home-page: https://github.com/gingerpayments/python-libmt94x
Author: Ginger Payments
Author-email: dev@gingerpayments.com
License: MIT
Platform: OS Independent
Classifier: Intended Audience :: Developers
Classifier: License :: OSI Approved :: MIT License
Classifier: Operating System :: OS Independent
Classifier: Topic :: Software Development :: Libraries :: Python Modules
Classifier: Development Status :: 5 - Production/Stable
Classifier: Programming Language :: Python
Classifier: Programming Language :: Python :: 2.7
